setup.py
Data_validation_v1.egg-info/.DS_Store
Data_validation_v1.egg-info/PKG-INFO
Data_validation_v1.egg-info/README.txt
Data_validation_v1.egg-info/SOURCES.txt
Data_validation_v1.egg-info/dependency_links.txt
Data_validation_v1.egg-info/not-zip-safe
Data_validation_v1.egg-info/requires.txt
Data_validation_v1.egg-info/top_level.txt
data_validation/__init__.py
data_validation/data_validation.py