Metadata-Version: 1.1
Name: Data-validation-v1
Version: 1.4
Summary: Data Validation package
Home-page: UNKNOWN
Author: Afiz Oyerinde
Author-email: ayodejioyerinde93@gmail.com
License: Free
Platform: UNKNOWN
Classifier: Programming Language :: Python :: 3
